sam/__init__.py
sam/sam.py
sam/utils.py
sam_pytorch-0.0.1.dist-info/LICENSE
sam_pytorch-0.0.1.dist-info/METADATA
sam_pytorch-0.0.1.dist-info/WHEEL
sam_pytorch-0.0.1.dist-info/top_level.txt
sam_pytorch-0.0.1.dist-info/RECORD
