Metadata-Version: 2.1
Name: sam-pytorch
Version: 0.0.1
Summary: NFNets, PyTorch
Home-page: https://github.com/tourdeml/sam
Author: Vaibhav Balloli
Author-email: tour.de.ml@protonmail.com
License: MIT
Keywords: optimizer,pytorch,sharpness aware minimization
Platform: UNKNOWN
Classifier: Development Status :: 4 - Beta
Classifier: Intended Audience :: Developers
Classifier: Topic :: Scientific/Engineering :: Artificial Intelligence
Classifier: License :: OSI Approved :: MIT License
Classifier: Programming Language :: Python :: 3.6
Classifier: Programming Language :: Python :: 3.7
Classifier: Programming Language :: Python :: 3.8
Requires-Dist: torch
